pymaibool/__init__.py
pymaibool/pymaibool.py
pymaibool-0.1.2.dist-info/LICENSE
pymaibool-0.1.2.dist-info/METADATA
pymaibool-0.1.2.dist-info/WHEEL
pymaibool-0.1.2.dist-info/top_level.txt
pymaibool-0.1.2.dist-info/RECORD
